CONTRIBUTING.md
MANIFEST.in
README.rst
setup.py
docs/HISTORY.txt
docs/LICENSE.GPL
docs/LICENSE.txt
eea/__init__.py
eea.versions.egg-info/PKG-INFO
eea.versions.egg-info/SOURCES.txt
eea.versions.egg-info/dependency_links.txt
eea.versions.egg-info/entry_points.txt
eea.versions.egg-info/namespace_packages.txt
eea.versions.egg-info/not-zip-safe
eea.versions.egg-info/requires.txt
eea.versions.egg-info/top_level.txt
eea/versions/README.txt
eea/versions/REFACTOR.txt
eea/versions/__init__.py
eea/versions/assign_version.pt
eea/versions/catalog.py
eea/versions/config.py
eea/versions/configure.zcml
eea/versions/debug.py
eea/versions/events.py
eea/versions/interfaces.py
eea/versions/marshaller.py
eea/versions/overrides.zcml
eea/versions/profiles.zcml
eea/versions/skins.zcml
eea/versions/utils.py
eea/versions/version.txt
eea/versions/versions.py
eea/versions/browser/__init__.py
eea/versions/browser/configure.zcml
eea/versions/browser/interfaces.py
eea/versions/browser/overrides.zcml
eea/versions/browser/view.py
eea/versions/browser/viewlets.py
eea/versions/browser/templates/versioning_id.pt
eea/versions/browser/templates/versioning_older.pt
eea/versions/browser/templates/versioning_status.pt
eea/versions/controlpanel/__init__.py
eea/versions/controlpanel/configure.zcml
eea/versions/controlpanel/interfaces.py
eea/versions/controlpanel/schema.py
eea/versions/controlpanel/tool.py
eea/versions/controlpanel/utils.py
eea/versions/controlpanel/views.py
eea/versions/controlpanel/vocabularies.py
eea/versions/controlpanel/template/view.pt
eea/versions/docs/versions.txt
eea/versions/locales/eea.pot
eea/versions/locales/update.sh
eea/versions/locales/bg/LC_MESSAGES/eea.po
eea/versions/locales/cs/LC_MESSAGES/eea.po
eea/versions/locales/da/LC_MESSAGES/eea.po
eea/versions/locales/de/LC_MESSAGES/eea.po
eea/versions/locales/el/LC_MESSAGES/eea.po
eea/versions/locales/en/LC_MESSAGES/eea.po
eea/versions/locales/es/LC_MESSAGES/eea.po
eea/versions/locales/et/LC_MESSAGES/eea.po
eea/versions/locales/eu/LC_MESSAGES/eea.po
eea/versions/locales/fi/LC_MESSAGES/eea.po
eea/versions/locales/fr/LC_MESSAGES/eea.po
eea/versions/locales/hu/LC_MESSAGES/eea.po
eea/versions/locales/is/LC_MESSAGES/eea.po
eea/versions/locales/it/LC_MESSAGES/eea.po
eea/versions/locales/kl/LC_MESSAGES/eea.po
